async_schedule/__init__.py
async_schedule/client.py
async_schedule/dispatcher.py
async_schedule/domain.py
async_schedule/op.py
async_schedule/worker.py
tests/__init__.py
tests/mock.py
tests/test_dispatcher.py
tests/test_operator.py
tests/test_worker.py
schedule_sdk-3.0.7.dist-info/METADATA
schedule_sdk-3.0.7.dist-info/WHEEL
schedule_sdk-3.0.7.dist-info/top_level.txt
schedule_sdk-3.0.7.dist-info/RECORD
