Metadata-Version: 2.1
Name: schedule-sdk
Version: 3.0.7
Requires-Dist: requests
Requires-Dist: redis
